{"info":{"_postman_id":"330c7bd8-0249-49f1-b3c0-a94d274aca00","name":"Carteiras","schema":"https://schema.getpostman.com/json/collection/v2.1.0/collection.json"},"item":[{"name":"Developers","item":[{"name":"ListarCarteiras","_postman_id":"883383b3-b622-4883-972c-79d475fe02b6","protocolProfileBehavior":{"disableBodyPruning":true},"request":{"method":"GET","header":[{"key":"DevKey","value":"Java-is-a-shit","type":"text"}],"url":{"raw":"{{Url}}{{carteira}}/api/v1/developers/enums/carteiras","host":["{{Url}}{{carteira}}"],"path":["api","v1","developers","enums","carteiras"]}},"response":[]},{"name":"ListarIndicadores","_postman_id":"7162a672-4bdb-45d4-a3f0-89960db0aa8a","protocolProfileBehavior":{"disableBodyPruning":true},"request":{"method":"GET","header":[{"key":"DevKey","value":"Java-is-a-shit","type":"text"}],"url":{"raw":"{{Url}}{{carteira}}/api/v1/developers/enums/carteiras","host":["{{Url}}{{carteira}}"],"path":["api","v1","developers","enums","carteiras"]}},"response":[]},{"name":"ListarMetricas","_postman_id":"ae13fa8b-01eb-4d92-9e79-1a4786c1d81e","protocolProfileBehavior":{"disableBodyPruning":true},"request":{"method":"GET","header":[{"key":"DevKey","value":"Java-is-a-shit","type":"text"}],"url":{"raw":"{{Url}}{{carteira}}/api/v1/developers/enums/carteiras","host":["{{Url}}{{carteira}}"],"path":["api","v1","developers","enums","carteiras"]}},"response":[]},{"name":"ListarPeriodicidades","_postman_id":"4d1cf915-33a7-4cd8-aad2-b27df8503b2f","protocolProfileBehavior":{"disableBodyPruning":true},"request":{"method":"GET","header":[{"key":"DevKey","value":"Java-is-a-shit","type":"text"}],"url":{"raw":"{{Url}}{{carteira}}/api/v1/developers/enums/carteiras","host":["{{Url}}{{carteira}}"],"path":["api","v1","developers","enums","carteiras"]}},"response":[]},{"name":"ListarQuebras","_postman_id":"85e1698c-0bd9-4efb-a3ce-c98911d1325d","protocolProfileBehavior":{"disableBodyPruning":true},"request":{"method":"GET","header":[{"key":"DevKey","value":"Java-is-a-shit","type":"text"}],"url":{"raw":"{{Url}}{{carteira}}/api/v1/developers/enums/carteiras","host":["{{Url}}{{carteira}}"],"path":["api","v1","developers","enums","carteiras"]}},"response":[]},{"name":"Seed","_postman_id":"88b55bc4-0eb8-493d-930d-fd485caf5473","protocolProfileBehavior":{"disableBodyPruning":true},"request":{"method":"POST","header":[{"key":"Funcional","value":"123456789","type":"text"},{"key":"DevKey","value":"Java-is-a-shit","type":"text"}],"url":{"raw":"{{Url}}{{carteira}}/api/v1/developers/seed","host":["{{Url}}{{carteira}}"],"path":["api","v1","developers","seed"]}},"response":[]}],"_postman_id":"f3d1f60e-3f55-4a07-ad68-19a7f8f346b4"},{"name":"Dashboard","item":[{"name":"carteiras","_postman_id":"eb0bc9f8-e10f-4c2a-be25-59bb56fe2272","protocolProfileBehavior":{"disableBodyPruning":true},"request":{"method":"GET","header":[{"key":"Funcional","value":"004506119","type":"text"}],"url":{"raw":"{{Url}}{{carteira}}/api/v1/dashboard/temas/negocios/carteiras/negocio.producao","host":["{{Url}}{{carteira}}"],"path":["api","v1","dashboard","temas","negocios","carteiras","negocio.producao"]}},"response":[]}],"_postman_id":"5b10e0bd-45e2-4f80-bde1-6cf365d9c5ee"}]}